LICENSE
README.md
rag_meter/__init__.py
rag_meter/adapters/__init__.py
rag_meter/adapters/arize/__init__.py
rag_meter/adapters/arize/arize_adapter.py
rag_meter/adapters/arize/models.py
rag_meter/adapters/common_pipeline.py
rag_meter/adapters/deepeval/__init__.py
rag_meter/adapters/deepeval/deepeval_adapter.py
rag_meter/adapters/deepeval/models.py
rag_meter/adapters/models.py
rag_meter/adapters/ragas/__init__.py
rag_meter/adapters/ragas/models.py
rag_meter/adapters/ragas/ragas_adapter.py
rag_meter/adapters/trulens/models.py
rag_meter/adapters/trulens/trulens_adapter.py
rag_meter/aggregator.py
rag_meter/cli/__init__.py
rag_meter/cli/main.py
rag_meter/constants.py
rag_meter/evaluation.py
rag_meter-0.1.1.dist-info/LICENSE
rag_meter-0.1.1.dist-info/METADATA
rag_meter-0.1.1.dist-info/WHEEL
rag_meter-0.1.1.dist-info/entry_points.txt
rag_meter-0.1.1.dist-info/RECORD
